python_git_wrapper/__init__.py
python_git_wrapper/branch.py
python_git_wrapper/commit.py
python_git_wrapper/exceptions.py
python_git_wrapper/git_service.py
python_git_wrapper/repository.py
python_git_wrapper/status.py
tests/__init__.py
tests/fixtures/__init__.py
tests/fixtures/repository.py
tests/git_service/__init__.py
tests/git_service/test_git_service.py
tests/repository/__init__.py
tests/repository/test_branches.py
tests/repository/test_init_repo.py
tests/repository/test_operation_repo.py
tests/repository/test_remote.py
python_git_wrapper-0.9.0.post2.dist-info/LICENSE
python_git_wrapper-0.9.0.post2.dist-info/METADATA
python_git_wrapper-0.9.0.post2.dist-info/WHEEL
python_git_wrapper-0.9.0.post2.dist-info/top_level.txt
python_git_wrapper-0.9.0.post2.dist-info/RECORD
