Metadata-Version: 2.1
Name: python-git-wrapper
Version: 0.9.0.post2
Summary: Simple git wrapper for python
Home-page: https://github.com/juanbenitopr/python-git-wrapper
Author: Juan Benito Pacheco Rubio
Author-email: juanbenito.pr@gmail.com
License: UNKNOWN
Platform: UNKNOWN
Classifier: Development Status :: 4 - Beta
Classifier: Intended Audience :: Developers
Classifier: License :: OSI Approved :: MIT License
Classifier: Topic :: Software Development :: Version Control :: Git
Classifier: Programming Language :: Python :: 3.7
Classifier: Programming Language :: Python :: 3.8
Classifier: Topic :: Software Development :: Libraries
Classifier: Topic :: Utilities
Requires-Python: >=3.7
